{
	"format_version": "1.12.0",
	"minecraft:geometry": [
		{
			"description": {
				"identifier": "geometry.unknown",
				"texture_width": 64,
				"texture_height": 64,
				"visible_bounds_width": 2,
				"visible_bounds_height": 3.5,
				"visible_bounds_offset": [0, 1.25, 0]
			},
			"bones": [
				{
					"name": "bb_main",
					"pivot": [0, 0, 0],
					"cubes": [
						{"origin": [-4, 27, -2], "size": [8, 8, 4], "uv": [20, 22]},
						{"origin": [-1, 24, -1], "size": [2, 4, 2], "uv": [40, 40]},
						{"origin": [1.75, 0, -1], "size": [2, 10, 2], "uv": [14, 32]},
						{"origin": [-3.75, 0, -1], "size": [2, 10, 2], "uv": [14, 32]}
					]
				},
				{
					"name": "Chest",
					"pivot": [0, 21.5, -1.25],
					"cubes": [
						{"origin": [-5, 17.5, -3.25], "size": [10, 8, 4], "pivot": [0, 21.5, -1.25], "rotation": [-15, 0, 0], "uv": [0, 0]},
						{"origin": [-4, 19.5, 0.75], "size": [8, 6, 1], "pivot": [0, 21.5, -1.25], "rotation": [-15, 0, 0], "uv": [24, 12]},
						{"origin": [-4, 18.5, -4.25], "size": [8, 6, 1], "pivot": [0, 21.5, -1.25], "rotation": [-15, 0, 0], "uv": [24, 12]}
					]
				},
				{
					"name": "Waist",
					"pivot": [0, 14, -1],
					"cubes": [
						{"origin": [-3, 10, 1], "size": [6, 6, 1], "pivot": [0, 14, -1], "rotation": [15, 0, 0], "uv": [28, 0]},
						{"origin": [-3, 9, -4], "size": [6, 10, 1], "pivot": [0, 14, -1], "rotation": [15, 0, 0], "uv": [0, 26]},
						{"origin": [-4, 9, -3], "size": [8, 10, 4], "pivot": [0, 14, -1], "rotation": [15, 0, 0], "uv": [0, 12]}
					]
				},
				{
					"name": "Spikes",
					"parent": "Waist",
					"pivot": [-0.25, 14, -1],
					"cubes": [
						{"origin": [-3, 14, 1], "size": [1, 1, 4], "pivot": [-5, 13, -2], "rotation": [35, 0, 0], "uv": [34, 34]},
						{"origin": [-3, 17.62611, 2.8062], "size": [1, 1, 2], "pivot": [-2.5, 18.15851, 2.70575], "rotation": [53.80286, 10.54794, 14.04397], "uv": [24, 19]},
						{"origin": [1, 14, 2], "size": [1, 1, 3], "pivot": [3, 14, -1], "rotation": [22.5, 0, 0], "uv": [38, 8]},
						{"origin": [1.5, 16.46475, 4.16163], "size": [1, 1, 2], "pivot": [1.5, 17.71475, 6.66163], "rotation": [5.07673, 9.96156, 0.88045], "uv": [24, 19]},
						{"origin": [-2.5, 10, 0], "size": [1, 1, 4], "pivot": [-1.5, 14, -3], "rotation": [22.5, 0, 0], "uv": [34, 34]},
						{"origin": [-2, 13.76923, 4.69237], "size": [1, 1, 2], "pivot": [-2, 14.01923, 6.19237], "rotation": [39.71128, 17.67415, 14.15251], "uv": [24, 19]},
						{"origin": [2.75, 12, 1], "size": [1, 1, 4], "pivot": [-0.25, 14, -1], "rotation": [2.5, 0, 0], "uv": [34, 34]}
					]
				},
				{
					"name": "LArm",
					"pivot": [6.5, 23.5, -0.5],
					"cubes": [
						{"origin": [5, 22, -10], "size": [3, 3, 1], "uv": [44, 0]},
						{"origin": [4.62352, 22.32632, -9.75741], "size": [1, 1, 4], "pivot": [5.12352, 22.82632, -7.75741], "rotation": [-7.5, -7.5, 0], "uv": [18, 40]},
						{"origin": [4.67368, 22, -5.97861], "size": [1, 1, 4], "pivot": [5.17368, 22.5, -3.97861], "rotation": [0, 7.5, 0], "uv": [40, 35]},
						{"origin": [6.0034, 24.21591, -5.96678], "size": [1, 1, 4], "pivot": [6.5034, 24.71591, -3.96678], "rotation": [-1.9914, 5.4501, 90.78177], "uv": [40, 30]},
						{"origin": [7.21789, 22, -5.99049], "size": [1, 1, 4], "pivot": [7.71789, 22.5, -3.99049], "rotation": [0, -5, 0], "uv": [40, 35]},
						{"origin": [6.00301, 24.1813, -9.81032], "size": [1, 1, 4], "pivot": [6.50301, 24.6813, -7.81032], "rotation": [3.0079, -4.54951, 90.69318], "uv": [6, 40]},
						{"origin": [5, 22, -2], "size": [3, 3, 3], "uv": [22, 34]},
						{"origin": [7.18294, 22.21789, -9.88101], "size": [1, 1, 4], "pivot": [7.68294, 22.71789, -7.88101], "rotation": [-5, 5, 0], "uv": [40, 20]}
					]
				},
				{
					"name": "RArm",
					"pivot": [-6.32929, 23.60805, -5],
					"cubes": [
						{"origin": [-7.93735, 21.81087, -5.99049], "size": [1, 1, 4], "pivot": [-7.43735, 22.31087, -3.99049], "rotation": [0, -5, 90], "uv": [28, 7]},
						{"origin": [-7.71946, 21.84582, -9.88101], "size": [1, 1, 4], "pivot": [-7.21946, 22.34582, -7.88101], "rotation": [-5, 5, 90], "uv": [0, 37]},
						{"origin": [-7.93735, 24.35508, -5.97861], "size": [1, 1, 4], "pivot": [-7.43735, 24.85508, -3.97861], "rotation": [0, 7.5, 90], "uv": [38, 3]},
						{"origin": [-7.61103, 24.40524, -9.75741], "size": [1, 1, 4], "pivot": [-7.11103, 24.90524, -7.75741], "rotation": [-7.5, -7.5, 90], "uv": [38, 15]},
						{"origin": [-7.75, 22, -10], "size": [3, 3, 1], "pivot": [-6.32929, 23.60805, -5], "rotation": [0, 0, 90], "uv": [44, 0]},
						{"origin": [-5.75619, 23.02876, -9.81228], "size": [1, 1, 4], "pivot": [-5.25619, 23.52876, -7.81228], "rotation": [2.5, -5, -180], "uv": [28, 7]},
						{"origin": [-7.75, 22.1, -2], "size": [3, 3, 3], "pivot": [-6.32929, 23.60805, -5], "rotation": [0, 0, 90], "uv": [22, 34]},
						{"origin": [-5.72124, 23.02876, -5.96873], "size": [1, 1, 4], "pivot": [-5.22124, 23.52876, -3.96873], "rotation": [-2.5, 5, -180], "uv": [30, 39]}
					]
				}
			]
		}
	]
}